demo/__init__.py
demo/test_file.py
demo/test_flask.py
lingopy/__init__.py
lingopy/lingopy.py
lingopy-0.1.0.1.dist-info/LICENSE
lingopy-0.1.0.1.dist-info/METADATA
lingopy-0.1.0.1.dist-info/WHEEL
lingopy-0.1.0.1.dist-info/top_level.txt
lingopy-0.1.0.1.dist-info/RECORD
