Metadata-Version: 2.1
Name: lingopy
Version: 0.1.0.1
Summary: Lingopy is a lightweight localization library for Python that helps you manage localized messages effortlessly.
Home-page: https://github.com/0x1618/lingopy-python
Author: Maksymilian Sawicz
Classifier: Programming Language :: Python :: 3
Classifier: License :: OSI Approved :: MIT License
Classifier: Operating System :: OS Independent
Requires-Python: >=3.0
License-File: LICENSE
